aiomexc/__init__.py
aiomexc/__main__.py
aiomexc/cli/__init__.py
aiomexc/cli/aiohttp_session.py
aiomexc/cli/credentials.py
aiomexc/cli/main.py
aiomexc/client.py
aiomexc/enums.py
aiomexc/exceptions.py
aiomexc/loggers.py
aiomexc/methods/__init__.py
aiomexc/methods/account.py
aiomexc/methods/base.py
aiomexc/methods/order.py
aiomexc/methods/ticker.py
aiomexc/methods/user_data_stream.py
aiomexc/retort.py
aiomexc/session/__init__.py
aiomexc/session/aiohttp.py
aiomexc/session/base.py
aiomexc/types/__init__.py
aiomexc/types/account.py
aiomexc/types/base.py
aiomexc/types/order.py
aiomexc/types/ticker.py
aiomexc/types/user_data_stream.py
aiomexc/ws/__init__.py
aiomexc/ws/connection.py
aiomexc/ws/credentials.py
aiomexc/ws/dispatcher.py
aiomexc/ws/messages/__init__.py
aiomexc/ws/messages/base.py
aiomexc/ws/messages/listen_key.py
aiomexc/ws/messages/private_deals.py
aiomexc/ws/messages/private_order.py
aiomexc/ws/messages/public_aggre_deals.py
aiomexc/ws/messages/subscription.py
aiomexc/ws/proto/__init__.py
aiomexc/ws/proto/message.py
aiomexc/ws/proto/private_account.py
aiomexc/ws/proto/private_deals.py
aiomexc/ws/proto/private_orders.py
aiomexc/ws/proto/public_aggre_book_ticker.py
aiomexc/ws/proto/public_aggre_deals.py
aiomexc/ws/proto/public_aggre_depths.py
aiomexc/ws/proto/public_book_ticker.py
aiomexc/ws/proto/public_book_tickers_batch.py
aiomexc/ws/proto/public_deals.py
aiomexc/ws/proto/public_increase_depths.py
aiomexc/ws/proto/public_increase_depths_batch.py
aiomexc/ws/proto/public_limit_depths.py
aiomexc/ws/proto/public_mini_ticker.py
aiomexc/ws/proto/public_mini_tickers.py
aiomexc/ws/proto/public_spot_kline.py
aiomexc/ws/session/__init__.py
aiomexc/ws/session/aiohttp.py
aiomexc/ws/session/base.py
aiomexc-0.2.16.dist-info/WHEEL
aiomexc-0.2.16.dist-info/entry_points.txt
aiomexc-0.2.16.dist-info/METADATA
aiomexc-0.2.16.dist-info/RECORD
