Metadata-Version: 2.3
Name: aiomexc
Version: 0.2.16
Summary: Asynchronous MEXC API wrapper
Keywords: mexc,api,client,wrapper,asyncio
Author: Sheldy
Author-email: Sheldy <chikibamtioma@gmail.com>
Classifier: Programming Language :: Python
Classifier: Programming Language :: Python :: Implementation :: CPython
Classifier: Programming Language :: Python :: 3
Classifier: Programming Language :: Python :: 3 :: Only
Classifier: Programming Language :: Python :: 3.11
Classifier: Programming Language :: Python :: 3.12
Classifier: Programming Language :: Python :: 3.13
Classifier: Operating System :: OS Independent
Classifier: Topic :: Software Development :: Libraries :: Application Frameworks
Classifier: Topic :: Software Development :: Libraries :: Python Modules
Classifier: Topic :: Software Development :: Libraries
Classifier: Topic :: Software Development
Classifier: Topic :: System :: Networking
Classifier: Topic :: System :: Distributed Computing
Classifier: Typing :: Typed
Classifier: Intended Audience :: Developers
Classifier: Intended Audience :: Information Technology
Classifier: Intended Audience :: System Administrators
Classifier: Environment :: Web Environment
Requires-Dist: adaptix~=3.0.0b11
Requires-Dist: aiohttp~=3.11.13
Requires-Dist: aiohttp-socks~=0.10.1
Requires-Dist: certifi>=2023.7.22
Requires-Dist: questionary~=2.1.0 ; extra == 'cli'
Requires-Dist: pure-protobuf~=3.1.3 ; extra == 'ws'
Requires-Python: >=3.11
Project-URL: Documentation, https://github.com/sheldygg/aiomexc
Project-URL: Homepage, https://github.com/sheldygg/aiomexc
Project-URL: Source, https://github.com/sheldygg/aiomexc
Project-URL: Tracker, https://github.com/sheldygg/aiomexc/issues
Provides-Extra: cli
Provides-Extra: ws
